quora_scraper/chromedriver
quora_scraper/scraper.py
quora_scraper-1.1.3.dist-info/METADATA
quora_scraper-1.1.3.dist-info/RECORD
quora_scraper-1.1.3.dist-info/WHEEL
quora_scraper-1.1.3.dist-info/entry_points.txt
quora_scraper-1.1.3.dist-info/top_level.txt
