Metadata-Version: 2.1
Name: quora-scraper
Version: 1.1.3
Summary: Python based code to scrap and download data from quora website: questions related to certain topics, answers given on certain questions and users profile data
Home-page: https://github.com/banyous/quora-scraper
Author: Youcef Benkhedda
Author-email: y_benkhedda@esi.dz
License: MIT
Download-URL: https://github.com/user/reponame/archive/v_01.tar.gz
Keywords: quora,topics,Q&A,user,scraper,download,answers,questions
Platform: UNKNOWN
Classifier: Development Status :: 3 - Alpha
Classifier: Intended Audience :: Developers
Classifier: Topic :: Software Development :: Build Tools
Classifier: License :: OSI Approved :: MIT License
Classifier: Programming Language :: Python :: 3.6
Requires-Dist: selenium
Requires-Dist: bs4
Requires-Dist: webdriver-manager
Requires-Dist: dateparser
Requires-Dist: userpaths
